napari_image_stacker/__init__.py
napari_image_stacker/_dock_widget.py
napari_image_stacker/_version.py
napari_image_stacker/_tests/__init__.py
napari_image_stacker/_tests/test_dock_widget.py
napari_image_stacker/_tests/test_function.py
napari_image_stacker-0.1.10.dist-info/LICENSE
napari_image_stacker-0.1.10.dist-info/METADATA
napari_image_stacker-0.1.10.dist-info/WHEEL
napari_image_stacker-0.1.10.dist-info/entry_points.txt
napari_image_stacker-0.1.10.dist-info/top_level.txt
napari_image_stacker-0.1.10.dist-info/RECORD
