Metadata-Version: 2.1
Name: napari-image-stacker
Version: 0.1.10
Summary: A plugin designed to convert multiple open layers into a stack or vice versa
Home-page: https://github.com/RobAnKo/napari-image-stacker
Author: Robin Koch, Marc Boucsein
Author-email: robin.koch@dkfz-heidelberg.de
License: BSD3
Project-URL: Bug Tracker, https://github.com/RobAnKo/napari-image-stacker/issues
Project-URL: Documentation, https://github.com/RobAnKo/napari-image-stacker#README.md
Project-URL: Source Code, https://github.com/RobAnKo/napari-image-stacker
Project-URL: User Support, https://github.com/RobAnKo/napari-image-stacker/issues
Platform: UNKNOWN
Classifier: Development Status :: 2 - Pre-Alpha
Classifier: Intended Audience :: Developers
Classifier: Framework :: napari
Classifier: Topic :: Software Development :: Testing
Classifier: Programming Language :: Python
Classifier: Programming Language :: Python :: 3
Classifier: Programming Language :: Python :: 3.7
Classifier: Programming Language :: Python :: 3.8
Classifier: Programming Language :: Python :: 3.9
Classifier: Operating System :: OS Independent
Classifier: License :: OSI Approved :: BSD License
Requires-Python: >=3.7
License-File: LICENSE
Requires-Dist: napari-plugin-engine (>=0.1.4)
Requires-Dist: numpy
